{
  "tag": "2020-08-29_122955",
  "event": {
    "event_type": "touch",
    "x": null,
    "y": null,
    "view": {
      "package": "org.wikipedia.alpha",
      "visible": true,
      "checkable": false,
      "child_count": 0,
      "editable": false,
      "clickable": true,
      "is_password": false,
      "focusable": true,
      "enabled": true,
      "content_description": null,
      "children": [],
      "focused": false,
      "bounds": [
        [
          42,
          883
        ],
        [
          1038,
          1009
        ]
      ],
      "resource_id": "org.wikipedia.alpha:id/login_create_account_button",
      "checked": false,
      "text": "JOIN WIKIPEDIA",
      "class": "android.widget.Button",
      "scrollable": false,
      "selected": false,
      "long_clickable": false,
      "parent": 29,
      "temp_id": 31,
      "size": "996*126",
      "signature": "[class]android.widget.Button[resource_id]org.wikipedia.alpha:id/login_create_account_button[text]JOIN WIKIPEDIA[enabled,,]",
      "view_str": "5c9317c6809bf4d51b203ddd957c7210",
      "content_free_signature": "[class]android.widget.Button[resource_id]org.wikipedia.alpha:id/login_create_account_button"
    }
  },
  "start_state": "5231334f93a8ca7573c3e42c634adce6",
  "stop_state": "e53caf7a3c4816a4c483b0811bdc129d",
  "event_str": "TouchEvent(state=5231334f93a8ca7573c3e42c634adce6, view=5c9317c6809bf4d51b203ddd957c7210)"
}