{
  "tag": "2020-08-29_091242",
  "state_str": "4e0c6410a035cadf5722bba84b203469",
  "state_str_content_free": "2151191b542640d41d90a3e1c35493f4",
  "foreground_activity": "com.habitrpg.android.habitica.debug/com.habitrpg.android.habitica.ui.activities.TaskFormActivity",
  "activity_stack": [
    "com.habitrpg.android.habitica.debug/com.habitrpg.android.habitica.ui.activities.TaskFormActivity",
    "com.habitrpg.android.habitica.debug/com.habitrpg.android.habitica.ui.activities.MainActivity"
  ],
  "background_services": [
    "com.google.android.networkstack.tethering/com.android.networkstack.tethering.TetheringService",
    "com.google.android.gms/.deviceconnection.service.DeviceConnectionWatcherService",
    "com.android.systemui/.keyguard.KeyguardService",
    "com.android.bluetooth/.btservice.AdapterService",
    "com.android.systemui/.ImageWallpaper",
    "com.google.android.inputmethod.latin/com.android.inputmethod.latin.spellcheck.AndroidSpellCheckerService",
    "com.google.android.gms/com.google.android.location.geocode.GeocodeService",
    "com.google.android.gms/.auth.setup.devicesignals.LockScreenService",
    "com.google.android.gms/.gcm.GcmService",
    "com.google.android.gms/.auth.proximity.firstparty.SystemMemoryCacheService",
    "com.android.phone/com.android.internal.telephony.CellularNetworkService",
    "com.google.android.gms/com.google.location.nearby.direct.service.NearbyDirectService",
    "com.google.android.gms/.chimera.PersistentBoundBrokerService",
    "com.android.bluetooth/.gatt.GattService",
    "com.google.android.gms/.chimera.GmsBoundBrokerService",
    "com.google.android.gms/.fido.fido2.pollux.CableAuthenticatorService",
    "com.google.android.googlequicksearchbox/com.google.android.apps.gsa.nowoverlayservice.DrawerOverlayService",
    "com.android.bluetooth/.pbap.BluetoothPbapService",
    "com.google.android.gms/.beacon.BleService",
    "com.google.android.gms/com.google.android.location.fused.FusedLocationService",
    "com.google.android.inputmethod.latin/com.google.android.libraries.micore.training.cache.service.TrainingCacheManagerService",
    "com.google.android.gms/.gcm.nts.SchedulerService",
    "com.google.android.ext.services/android.ext.services.autofill.InlineSuggestionRenderServiceImpl",
    "com.android.bluetooth/.a2dp.A2dpService",
    "com.google.android.providers.media.module/com.android.providers.media.fuse.ExternalStorageServiceImpl",
    "com.google.android.gms/.cast.media.CastMediaRouteProviderService",
    "io.github.ylimit.droidbotapp/io.github.privacystreams.accessibility.PSAccessibilityService",
    "com.google.android.gms/com.google.android.location.geofencer.service.GeofenceProviderService",
    "com.google.android.gms/.thunderbird.EmergencyPersistentService",
    "com.google.android.apps.nexuslauncher/com.android.launcher3.notification.NotificationListener",
    "com.android.systemui/.SystemUIService",
    "com.google.android.gms/.nearby.exposurenotification.service.ExposureMatchingService",
    "android/.hardware.location.GeofenceHardwareService",
    "com.android.se/.SecureElementService",
    "com.google.android.gms/.chimera.PersistentDirectBootAwareApiService",
    "com.android.bluetooth/.hid.HidDeviceService",
    "com.google.android.ext.services/android.ext.services.notification.Assistant",
    "com.google.android.gms/.auth.trustagent.GoogleTrustAgent",
    "com.google.android.gms/.location.persistent.LocationPersistentService",
    "com.google.android.gms/.nearby.discovery.service.DiscoveryService",
    "com.google.android.gms/com.google.android.location.internal.PendingIntentCallbackService",
    "com.google.android.gms/.nearby.messages.service.NearbyMessagesService",
    "com.android.server.telecom/.components.BluetoothPhoneService",
    "com.google.android.gms/com.google.android.location.internal.server.GoogleLocationService",
    "com.google.android.gms/com.google.android.contextmanager.service.ContextManagerService",
    "com.android.systemui/.dump.SystemUIAuxiliaryDumpService",
    "com.google.android.gms/com.google.android.location.network.NetworkLocationService",
    "com.android.stk/.StkAppService",
    "com.google.android.gms/com.google.android.location.internal.GoogleLocationManagerService",
    "com.google.android.inputmethod.latin/com.android.inputmethod.latin.LatinIME",
    "com.android.phone/com.android.internal.telephony.dataconnection.CellularDataService",
    "com.android.service.ims/.RcsService",
    "com.android.server.telecom/.components.TelecomService",
    "com.google.android.networkstack/com.android.server.NetworkStackService",
    "com.android.bluetooth/.hfp.HeadsetService",
    "com.google.android.googlequicksearchbox/com.google.android.voiceinteraction.GsaVoiceInteractionService",
    "com.android.emulator.multidisplay/.MultiDisplayService",
    "com.android.vending/com.google.android.finsky.setup.PlaySetupServiceV2",
    "com.android.phone/.vvm.RemoteVvmTaskManager",
    "com.android.ons/.OpportunisticNetworkService",
    "com.google.android.apps.messaging/.shared.datamodel.action.execution.ActionExecutorImpl",
    "com.google.android.gms/.common.stats.GmsCoreStatsService",
    "com.google.android.gms/com.google.android.location.internal.server.HardwareArProviderService",
    "com.android.bluetooth/.map.BluetoothMapService",
    "com.android.phone/com.android.services.telephony.sip.components.TelephonySipService",
    "com.android.phone/.TelephonyDebugService",
    "com.android.bluetooth/.hid.HidHostService",
    "com.android.bluetooth/.opp.BluetoothOppService",
    "com.android.bluetooth/.pan.PanService",
    "com.android.bluetooth/.avrcp.AvrcpTargetService",
    "com.google.android.apps.nexuslauncher/com.android.quickstep.TouchInteractionService",
    "com.google.android.cellbroadcastservice/com.android.cellbroadcastservice.DefaultCellBroadcastService",
    "com.google.android.setupwizard/.compat.SetupCompatService"
  ],
  "views": [
    {
      "package": "com.habitrpg.android.habitica.debug",
      "visible": true,
      "checkable": false,
      "child_count": 3,
      "editable": false,
      "clickable": false,
      "is_password": false,
      "focusable": false,
      "enabled": true,
      "content_description": null,
      "children": [
        1,
        79,
        80
      ],
      "focused": false,
      "bounds": [
        [
          0,
          0
        ],
        [
          1080,
          1920
        ]
      ],
      "resource_id": null,
      "checked": false,
      "text": null,
      "class": "android.widget.FrameLayout",
      "scrollable": false,
      "selected": false,
      "long_clickable": false,
      "parent": -1,
      "temp_id": 0,
      "size": "1080*1920",
      "signature": "[class]android.widget.FrameLayout[resource_id]None[text]None[enabled,,]",
      "view_str": "499252169a48f072abf8ed0a35dcd59f",
      "content_free_signature": "[class]android.widget.FrameLayout[resource_id]None"
    },
    {
      "package": "com.habitrpg.android.habitica.debug",
      "visible": true,
      "checkable": false,
      "child_count": 1,
      "editable": false,
      "clickable": false,
      "is_password": false,
      "focusable": false,
      "enabled": true,
      "content_description": null,
      "children": [
        2
      ],
      "focused": false,
      "bounds": [
        [
          0,
          0
        ],
        [
          1080,
          1794
        ]
      ],
      "resource_id": null,
      "checked": false,
      "text": null,
      "class": "android.widget.LinearLayout",
      "scrollable": false,
      "selected": false,
      "long_clickable": false,
      "parent": 0,
      "temp_id": 1,
      "size": "1080*1794",
      "signature": "[class]android.widget.LinearLayout[resource_id]None[text]None[enabled,,]",
      "view_str": "01ef280a6a3c1433dd4bffb1e2373c88",
      "content_free_signature": "[class]android.widget.LinearLayout[resource_id]None"
    },
    {
      "package": "com.habitrpg.android.habitica.debug",
      "visible": true,
      "checkable": false,
      "child_count": 1,
      "editable": false,
      "clickable": false,
      "is_password": false,
      "focusable": false,
      "enabled": true,
      "content_description": null,
      "children": [
        3
      ],
      "focused": false,
      "bounds": [
        [
          0,
          63
        ],
        [
          1080,
          1794
        ]
      ],
      "resource_id": null,
      "checked": false,
      "text": null,
      "class": "android.widget.FrameLayout",
      "scrollable": false,
      "selected": false,
      "long_clickable": false,
      "parent": 1,
      "temp_id": 2,
      "size": "1080*1731",
      "signature": "[class]android.widget.FrameLayout[resource_id]None[text]None[enabled,,]",
      "view_str": "9f55ae0db72b840a6f45912411ef9488",
      "content_free_signature": "[class]android.widget.FrameLayout[resource_id]None"
    },
    {
      "package": "com.habitrpg.android.habitica.debug",
      "visible": true,
      "checkable": false,
      "child_count": 1,
      "editable": false,
      "clickable": false,
      "is_password": false,
      "focusable": false,
      "enabled": true,
      "content_description": null,
      "children": [
        4
      ],
      "focused": false,
      "bounds": [
        [
          0,
          63
        ],
        [
          1080,
          1794
        ]
      ],
      "resource_id": "com.habitrpg.android.habitica.debug:id/action_bar_root",
      "checked": false,
      "text": null,
      "class": "android.widget.LinearLayout",
      "scrollable": false,
      "selected": false,
      "long_clickable": false,
      "parent": 2,
      "temp_id": 3,
      "size": "1080*1731",
      "signature": "[class]android.widget.LinearLayout[resource_id]com.habitrpg.android.habitica.debug:id/action_bar_root[text]None[enabled,,]",
      "view_str": "d9fbd0d118096ebae49dbb71c53bf1b2",
      "content_free_signature": "[class]android.widget.LinearLayout[resource_id]com.habitrpg.android.habitica.debug:id/action_bar_root"
    },
    {
      "package": "com.habitrpg.android.habitica.debug",
      "visible": true,
      "checkable": false,
      "child_count": 1,
      "editable": false,
      "clickable": false,
      "is_password": false,
      "focusable": false,
      "enabled": true,
      "content_description": null,
      "children": [
        5
      ],
      "focused": false,
      "bounds": [
        [
          0,
          63
        ],
        [
          1080,
          1794
        ]
      ],
      "resource_id": "android:id/content",
      "checked": false,
      "text": null,
      "class": "android.widget.FrameLayout",
      "scrollable": false,
      "selected": false,
      "long_clickable": false,
      "parent": 3,
      "temp_id": 4,
      "size": "1080*1731",
      "signature": "[class]android.widget.FrameLayout[resource_id]android:id/content[text]None[enabled,,]",
      "view_str": "f03d01c57b268ac9100a5c6193f5dcec",
      "content_free_signature": "[class]android.widget.FrameLayout[resource_id]android:id/content"
    },
    {
      "package": "com.habitrpg.android.habitica.debug",
      "visible": true,
      "checkable": false,
      "child_count": 2,
      "editable": false,
      "clickable": false,
      "is_password": false,
      "focusable": false,
      "enabled": true,
      "content_description": null,
      "children": [
        6,
        12
      ],
      "focused": false,
      "bounds": [
        [
          0,
          63
        ],
        [
          1080,
          1794
        ]
      ],
      "resource_id": null,
      "checked": false,
      "text": null,
      "class": "android.widget.LinearLayout",
      "scrollable": false,
      "selected": false,
      "long_clickable": false,
      "parent": 4,
      "temp_id": 5,
      "size": "1080*1731",
      "signature": "[class]android.widget.LinearLayout[resource_id]None[text]None[enabled,,]",
      "view_str": "f9a989263a1af08ecef89e52212df2ee",
      "content_free_signature": "[class]android.widget.LinearLayout[resource_id]None"
    },
    {
      "package": "com.habitrpg.android.habitica.debug",
      "visible": true,
      "checkable": false,
      "child_count": 1,
      "editable": false,
      "clickable": false,
      "is_password": false,
      "focusable": false,
      "enabled": true,
      "content_description": null,
      "children": [
        7
      ],
      "focused": false,
      "bounds": [
        [
          0,
          63
        ],
        [
          1080,
          210
        ]
      ],
      "resource_id": null,
      "checked": false,
      "text": null,
      "class": "android.widget.LinearLayout",
      "scrollable": false,
      "selected": false,
      "long_clickable": false,
      "parent": 5,
      "temp_id": 6,
      "size": "1080*147",
      "signature": "[class]android.widget.LinearLayout[resource_id]None[text]None[enabled,,]",
      "view_str": "95d361d516ecb676dff36dbf2a37a43e",
      "content_free_signature": "[class]android.widget.LinearLayout[resource_id]None"
    },
    {
      "package": "com.habitrpg.android.habitica.debug",
      "visible": true,
      "checkable": false,
      "child_count": 2,
      "editable": false,
      "clickable": false,
      "is_password": false,
      "focusable": false,
      "enabled": true,
      "content_description": null,
      "children": [
        8,
        9
      ],
      "focused": false,
      "bounds": [
        [
          0,
          63
        ],
        [
          1080,
          210
        ]
      ],
      "resource_id": "com.habitrpg.android.habitica.debug:id/toolbar",
      "checked": false,
      "text": null,
      "class": "android.view.ViewGroup",
      "scrollable": false,
      "selected": false,
      "long_clickable": false,
      "parent": 6,
      "temp_id": 7,
      "size": "1080*147",
      "signature": "[class]android.view.ViewGroup[resource_id]com.habitrpg.android.habitica.debug:id/toolbar[text]None[enabled,,]",
      "view_str": "056a595de54ebb5452cd09c1315e4970",
      "content_free_signature": "[class]android.view.ViewGroup[resource_id]com.habitrpg.android.habitica.debug:id/toolbar"
    },
    {
      "package": "com.habitrpg.android.habitica.debug",
      "visible": true,
      "checkable": false,
      "child_count": 0,
      "editable": false,
      "clickable": true,
      "is_password": false,
      "focusable": true,
      "enabled": true,
      "content_description": "Navigate up",
      "children": [],
      "focused": false,
      "bounds": [
        [
          0,
          63
        ],
        [
          147,
          210
        ]
      ],
      "resource_id": null,
      "checked": false,
      "text": null,
      "class": "android.widget.ImageButton",
      "scrollable": false,
      "selected": false,
      "long_clickable": false,
      "parent": 7,
      "temp_id": 8,
      "size": "147*147",
      "signature": "[class]android.widget.ImageButton[resource_id]None[text]None[enabled,,]",
      "view_str": "2b3e96cfa0873a33e9a6613efa2012f6",
      "content_free_signature": "[class]android.widget.ImageButton[resource_id]None"
    },
    {
      "package": "com.habitrpg.android.habitica.debug",
      "visible": true,
      "checkable": false,
      "child_count": 2,
      "editable": false,
      "clickable": false,
      "is_password": false,
      "focusable": false,
      "enabled": true,
      "content_description": null,
      "children": [
        10,
        11
      ],
      "focused": false,
      "bounds": [
        [
          731,
          63
        ],
        [
          1080,
          210
        ]
      ],
      "resource_id": null,
      "checked": false,
      "text": null,
      "class": "androidx.appcompat.widget.LinearLayoutCompat",
      "scrollable": false,
      "selected": false,
      "long_clickable": false,
      "parent": 7,
      "temp_id": 9,
      "size": "349*147",
      "signature": "[class]androidx.appcompat.widget.LinearLayoutCompat[resource_id]None[text]None[enabled,,]",
      "view_str": "507e2be78ea0774666253d3c7d53bc75",
      "content_free_signature": "[class]androidx.appcompat.widget.LinearLayoutCompat[resource_id]None"
    },
    {
      "package": "com.habitrpg.android.habitica.debug",
      "visible": true,
      "checkable": false,
      "child_count": 0,
      "editable": false,
      "clickable": true,
      "is_password": false,
      "focusable": true,
      "enabled": true,
      "content_description": null,
      "children": [],
      "focused": false,
      "bounds": [
        [
          731,
          73
        ],
        [
          925,
          199
        ]
      ],
      "resource_id": "com.habitrpg.android.habitica.debug:id/action_delete",
      "checked": false,
      "text": "DELETE",
      "class": "android.widget.TextView",
      "scrollable": false,
      "selected": false,
      "long_clickable": false,
      "parent": 9,
      "temp_id": 10,
      "size": "194*126",
      "signature": "[class]android.widget.TextView[resource_id]com.habitrpg.android.habitica.debug:id/action_delete[text]DELETE[enabled,,]",
      "view_str": "50beca786b192d394c248339677ae6f1",
      "content_free_signature": "[class]android.widget.TextView[resource_id]com.habitrpg.android.habitica.debug:id/action_delete"
    },
    {
      "package": "com.habitrpg.android.habitica.debug",
      "visible": true,
      "checkable": false,
      "child_count": 0,
      "editable": false,
      "clickable": true,
      "is_password": false,
      "focusable": true,
      "enabled": true,
      "content_description": null,
      "children": [],
      "focused": false,
      "bounds": [
        [
          925,
          73
        ],
        [
          1080,
          199
        ]
      ],
      "resource_id": "com.habitrpg.android.habitica.debug:id/action_save",
      "checked": false,
      "text": "SAVE",
      "class": "android.widget.TextView",
      "scrollable": false,
      "selected": false,
      "long_clickable": false,
      "parent": 9,
      "temp_id": 11,
      "size": "155*126",
      "signature": "[class]android.widget.TextView[resource_id]com.habitrpg.android.habitica.debug:id/action_save[text]SAVE[enabled,,]",
      "view_str": "3d221d3da68bbd2a3b32904f2f7b4757",
      "content_free_signature": "[class]android.widget.TextView[resource_id]com.habitrpg.android.habitica.debug:id/action_save"
    },
    {
      "package": "com.habitrpg.android.habitica.debug",
      "visible": true,
      "checkable": false,
      "child_count": 1,
      "editable": false,
      "clickable": false,
      "is_password": false,
      "focusable": true,
      "enabled": true,
      "content_description": null,
      "children": [
        13
      ],
      "focused": false,
      "bounds": [
        [
          0,
          210
        ],
        [
          1080,
          1794
        ]
      ],
      "resource_id": "com.habitrpg.android.habitica.debug:id/scroll_view",
      "checked": false,
      "text": null,
      "class": "android.widget.ScrollView",
      "scrollable": true,
      "selected": false,
      "long_clickable": false,
      "parent": 5,
      "temp_id": 12,
      "size": "1080*1584",
      "signature": "[class]android.widget.ScrollView[resource_id]com.habitrpg.android.habitica.debug:id/scroll_view[text]None[enabled,,]",
      "view_str": "65abdda53c9e660bde4a2a13b4b72915",
      "content_free_signature": "[class]android.widget.ScrollView[resource_id]com.habitrpg.android.habitica.debug:id/scroll_view"
    },
    {
      "package": "com.habitrpg.android.habitica.debug",
      "visible": true,
      "checkable": false,
      "child_count": 2,
      "editable": false,
      "clickable": false,
      "is_password": false,
      "focusable": false,
      "enabled": true,
      "content_description": null,
      "children": [
        14,
        21
      ],
      "focused": false,
      "bounds": [
        [
          0,
          210
        ],
        [
          1080,
          1794
        ]
      ],
      "resource_id": null,
      "checked": false,
      "text": null,
      "class": "android.widget.LinearLayout",
      "scrollable": false,
      "selected": false,
      "long_clickable": false,
      "parent": 12,
      "temp_id": 13,
      "size": "1080*1584",
      "signature": "[class]android.widget.LinearLayout[resource_id]None[text]None[enabled,,]",
      "view_str": "e44e1e0346ba0c8d41ee1c83347d2ac8",
      "content_free_signature": "[class]android.widget.LinearLayout[resource_id]None"
    },
    {
      "package": "com.habitrpg.android.habitica.debug",
      "visible": true,
      "checkable": false,
      "child_count": 2,
      "editable": false,
      "clickable": false,
      "is_password": false,
      "focusable": false,
      "enabled": true,
      "content_description": null,
      "children": [
        15,
        18
      ],
      "focused": false,
      "bounds": [
        [
          0,
          210
        ],
        [
          1080,
          736
        ]
      ],
      "resource_id": "com.habitrpg.android.habitica.debug:id/upper_text_wrapper",
      "checked": false,
      "text": null,
      "class": "android.widget.LinearLayout",
      "scrollable": false,
      "selected": false,
      "long_clickable": false,
      "parent": 13,
      "temp_id": 14,
      "size": "1080*526",
      "signature": "[class]android.widget.LinearLayout[resource_id]com.habitrpg.android.habitica.debug:id/upper_text_wrapper[text]None[enabled,,]",
      "view_str": "78fb9dfb13e504469daf2bace5422d5e",
      "content_free_signature": "[class]android.widget.LinearLayout[resource_id]com.habitrpg.android.habitica.debug:id/upper_text_wrapper"
    },
    {
      "package": "com.habitrpg.android.habitica.debug",
      "visible": true,
      "checkable": false,
      "child_count": 1,
      "editable": false,
      "clickable": false,
      "is_password": false,
      "focusable": false,
      "enabled": true,
      "content_description": null,
      "children": [
        16
      ],
      "focused": false,
      "bounds": [
        [
          42,
          210
        ],
        [
          1038,
          397
        ]
      ],
      "resource_id": "com.habitrpg.android.habitica.debug:id/text_input_layout",
      "checked": false,
      "text": null,
      "class": "android.widget.LinearLayout",
      "scrollable": false,
      "selected": false,
      "long_clickable": false,
      "parent": 14,
      "temp_id": 15,
      "size": "996*187",
      "signature": "[class]android.widget.LinearLayout[resource_id]com.habitrpg.android.habitica.debug:id/text_input_layout[text]None[enabled,,]",
      "view_str": "10814129e12cf0d61f3867659d8fe249",
      "content_free_signature": "[class]android.widget.LinearLayout[resource_id]com.habitrpg.android.habitica.debug:id/text_input_layout"
    },
    {
      "package": "com.habitrpg.android.habitica.debug",
      "visible": true,
      "checkable": false,
      "child_count": 1,
      "editable": false,
      "clickable": false,
      "is_password": false,
      "focusable": false,
      "enabled": true,
      "content_description": null,
      "children": [
        17
      ],
      "focused": false,
      "bounds": [
        [
          42,
          239
        ],
        [
          1038,
          397
        ]
      ],
      "resource_id": null,
      "checked": false,
      "text": null,
      "class": "android.widget.FrameLayout",
      "scrollable": false,
      "selected": false,
      "long_clickable": false,
      "parent": 15,
      "temp_id": 16,
      "size": "996*158",
      "signature": "[class]android.widget.FrameLayout[resource_id]None[text]None[enabled,,]",
      "view_str": "1ef522c145276b10f23b10d6f054d6d2",
      "content_free_signature": "[class]android.widget.FrameLayout[resource_id]None"
    },
    {
      "package": "com.habitrpg.android.habitica.debug",
      "visible": true,
      "checkable": false,
      "child_count": 0,
      "editable": true,
      "clickable": true,
      "is_password": false,
      "focusable": true,
      "enabled": true,
      "content_description": null,
      "children": [],
      "focused": false,
      "bounds": [
        [
          42,
          239
        ],
        [
          1038,
          397
        ]
      ],
      "resource_id": "com.habitrpg.android.habitica.debug:id/text_edit_text",
      "checked": false,
      "text": "GfStretching",
      "class": "android.widget.EditText",
      "scrollable": false,
      "selected": false,
      "long_clickable": true,
      "parent": 16,
      "temp_id": 17,
      "size": "996*158",
      "signature": "[class]android.widget.EditText[resource_id]com.habitrpg.android.habitica.debug:id/text_edit_text[text]GfStretching[enabled,,]",
      "view_str": "b703b5b3e612a5b8abe2eb897522ee4e",
      "content_free_signature": "[class]android.widget.EditText[resource_id]com.habitrpg.android.habitica.debug:id/text_edit_text"
    },
    {
      "package": "com.habitrpg.android.habitica.debug",
      "visible": true,
      "checkable": false,
      "child_count": 1,
      "editable": false,
      "clickable": false,
      "is_password": false,
      "focusable": false,
      "enabled": true,
      "content_description": null,
      "children": [
        19
      ],
      "focused": false,
      "bounds": [
        [
          42,
          397
        ],
        [
          1038,
          694
        ]
      ],
      "resource_id": "com.habitrpg.android.habitica.debug:id/notes_input_layout",
      "checked": false,
      "text": null,
      "class": "android.widget.LinearLayout",
      "scrollable": false,
      "selected": false,
      "long_clickable": false,
      "parent": 14,
      "temp_id": 18,
      "size": "996*297",
      "signature": "[class]android.widget.LinearLayout[resource_id]com.habitrpg.android.habitica.debug:id/notes_input_layout[text]None[enabled,,]",
      "view_str": "1cd8ebcaad2366adc29a48e5138cc685",
      "content_free_signature": "[class]android.widget.LinearLayout[resource_id]com.habitrpg.android.habitica.debug:id/notes_input_layout"
    },
    {
      "package": "com.habitrpg.android.habitica.debug",
      "visible": true,
      "checkable": false,
      "child_count": 1,
      "editable": false,
      "clickable": false,
      "is_password": false,
      "focusable": false,
      "enabled": true,
      "content_description": null,
      "children": [
        20
      ],
      "focused": false,
      "bounds": [
        [
          42,
          426
        ],
        [
          1038,
          694
        ]
      ],
      "resource_id": null,
      "checked": false,
      "text": null,
      "class": "android.widget.FrameLayout",
      "scrollable": false,
      "selected": false,
      "long_clickable": false,
      "parent": 18,
      "temp_id": 19,
      "size": "996*268",
      "signature": "[class]android.widget.FrameLayout[resource_id]None[text]None[enabled,,]",
      "view_str": "96dfb9a38c0056844db084ff1b386cf7",
      "content_free_signature": "[class]android.widget.FrameLayout[resource_id]None"
    },
    {
      "package": "com.habitrpg.android.habitica.debug",
      "visible": true,
      "checkable": false,
      "child_count": 0,
      "editable": true,
      "clickable": true,
      "is_password": false,
      "focusable": true,
      "enabled": true,
      "content_description": null,
      "children": [],
      "focused": true,
      "bounds": [
        [
          42,
          426
        ],
        [
          1038,
          694
        ]
      ],
      "resource_id": "com.habitrpg.android.habitica.debug:id/notes_edit_text",
      "checked": false,
      "text": "Shf",
      "class": "android.widget.EditText",
      "scrollable": false,
      "selected": false,
      "long_clickable": true,
      "parent": 19,
      "temp_id": 20,
      "size": "996*268",
      "signature": "[class]android.widget.EditText[resource_id]com.habitrpg.android.habitica.debug:id/notes_edit_text[text]Shf[enabled,,]",
      "view_str": "0b468f3759ecb42c9b2958216b8c0f15",
      "content_free_signature": "[class]android.widget.EditText[resource_id]com.habitrpg.android.habitica.debug:id/notes_edit_text"
    },
    {
      "package": "com.habitrpg.android.habitica.debug",
      "visible": true,
      "checkable": false,
      "child_count": 12,
      "editable": false,
      "clickable": false,
      "is_password": false,
      "focusable": false,
      "enabled": true,
      "content_description": null,
      "children": [
        22,
        23,
        27,
        28,
        41,
        42,
        65,
        66,
        72,
        73,
        77,
        78
      ],
      "focused": false,
      "bounds": [
        [
          42,
          736
        ],
        [
          1038,
          1794
        ]
      ],
      "resource_id": null,
      "checked": false,
      "text": null,
      "class": "android.widget.LinearLayout",
      "scrollable": false,
      "selected": false,
      "long_clickable": false,
      "parent": 13,
      "temp_id": 21,
      "size": "996*1058",
      "signature": "[class]android.widget.LinearLayout[resource_id]None[text]None[enabled,,]",
      "view_str": "b37a8c246ff8561beb35339799b616bf",
      "content_free_signature": "[class]android.widget.LinearLayout[resource_id]None"
    },
    {
      "package": "com.habitrpg.android.habitica.debug",
      "visible": true,
      "checkable": false,
      "child_count": 0,
      "editable": false,
      "clickable": false,
      "is_password": false,
      "focusable": false,
      "enabled": true,
      "content_description": null,
      "children": [],
      "focused": false,
      "bounds": [
        [
          42,
          778
        ],
        [
          1038,
          835
        ]
      ],
      "resource_id": "com.habitrpg.android.habitica.debug:id/checklist_title",
      "checked": false,
      "text": "Checklist",
      "class": "android.widget.TextView",
      "scrollable": false,
      "selected": false,
      "long_clickable": false,
      "parent": 21,
      "temp_id": 22,
      "size": "996*57",
      "signature": "[class]android.widget.TextView[resource_id]com.habitrpg.android.habitica.debug:id/checklist_title[text]Checklist[enabled,,]",
      "view_str": "3417f366616142056155bebca32e8579",
      "content_free_signature": "[class]android.widget.TextView[resource_id]com.habitrpg.android.habitica.debug:id/checklist_title"
    },
    {
      "package": "com.habitrpg.android.habitica.debug",
      "visible": true,
      "checkable": false,
      "child_count": 1,
      "editable": false,
      "clickable": false,
      "is_password": false,
      "focusable": false,
      "enabled": true,
      "content_description": null,
      "children": [
        24
      ],
      "focused": false,
      "bounds": [
        [
          42,
          856
        ],
        [
          1038,
          977
        ]
      ],
      "resource_id": "com.habitrpg.android.habitica.debug:id/checklist_container",
      "checked": false,
      "text": null,
      "class": "android.widget.LinearLayout",
      "scrollable": false,
      "selected": false,
      "long_clickable": false,
      "parent": 21,
      "temp_id": 23,
      "size": "996*121",
      "signature": "[class]android.widget.LinearLayout[resource_id]com.habitrpg.android.habitica.debug:id/checklist_container[text]None[enabled,,]",
      "view_str": "e8316b97c718c557d5d18acf0e0cb1d4",
      "content_free_signature": "[class]android.widget.LinearLayout[resource_id]com.habitrpg.android.habitica.debug:id/checklist_container"
    },
    {
      "package": "com.habitrpg.android.habitica.debug",
      "visible": true,
      "checkable": false,
      "child_count": 2,
      "editable": false,
      "clickable": false,
      "is_password": false,
      "focusable": false,
      "enabled": true,
      "content_description": null,
      "children": [
        25,
        26
      ],
      "focused": false,
      "bounds": [
        [
          42,
          856
        ],
        [
          1038,
          956
        ]
      ],
      "resource_id": null,
      "checked": false,
      "text": null,
      "class": "android.widget.LinearLayout",
      "scrollable": false,
      "selected": false,
      "long_clickable": false,
      "parent": 23,
      "temp_id": 24,
      "size": "996*100",
      "signature": "[class]android.widget.LinearLayout[resource_id]None[text]None[enabled,,]",
      "view_str": "4ea21354b4903202700ab8484ab2c01f",
      "content_free_signature": "[class]android.widget.LinearLayout[resource_id]None"
    },
    {
      "package": "com.habitrpg.android.habitica.debug",
      "visible": true,
      "checkable": false,
      "child_count": 0,
      "editable": false,
      "clickable": true,
      "is_password": false,
      "focusable": true,
      "enabled": true,
      "content_description": "Delete\u2026",
      "children": [],
      "focused": false,
      "bounds": [
        [
          42,
          866
        ],
        [
          142,
          945
        ]
      ],
      "resource_id": "com.habitrpg.android.habitica.debug:id/button",
      "checked": false,
      "text": null,
      "class": "android.widget.ImageButton",
      "scrollable": false,
      "selected": false,
      "long_clickable": false,
      "parent": 24,
      "temp_id": 25,
      "size": "100*79",
      "signature": "[class]android.widget.ImageButton[resource_id]com.habitrpg.android.habitica.debug:id/button[text]None[enabled,,]",
      "view_str": "9da425814df11e07f89c56c7aab186c4",
      "content_free_signature": "[class]android.widget.ImageButton[resource_id]com.habitrpg.android.habitica.debug:id/button"
    },
    {
      "package": "com.habitrpg.android.habitica.debug",
      "visible": true,
      "checkable": false,
      "child_count": 0,
      "editable": true,
      "clickable": true,
      "is_password": false,
      "focusable": true,
      "enabled": true,
      "content_description": null,
      "children": [],
      "focused": false,
      "bounds": [
        [
          184,
          880
        ],
        [
          1038,
          931
        ]
      ],
      "resource_id": "com.habitrpg.android.habitica.debug:id/edit_text",
      "checked": false,
      "text": "New checklist entry",
      "class": "android.widget.EditText",
      "scrollable": false,
      "selected": false,
      "long_clickable": true,
      "parent": 24,
      "temp_id": 26,
      "size": "854*51",
      "signature": "[class]android.widget.EditText[resource_id]com.habitrpg.android.habitica.debug:id/edit_text[text]New checklist entry[enabled,,]",
      "view_str": "0abea9437d41af94c3afa9b56ef504ae",
      "content_free_signature": "[class]android.widget.EditText[resource_id]com.habitrpg.android.habitica.debug:id/edit_text"
    },
    {
      "package": "com.habitrpg.android.habitica.debug",
      "visible": true,
      "checkable": false,
      "child_count": 0,
      "editable": false,
      "clickable": false,
      "is_password": false,
      "focusable": false,
      "enabled": true,
      "content_description": null,
      "children": [],
      "focused": false,
      "bounds": [
        [
          42,
          1019
        ],
        [
          1038,
          1076
        ]
      ],
      "resource_id": "com.habitrpg.android.habitica.debug:id/task_difficulty_title",
      "checked": false,
      "text": "Difficulty",
      "class": "android.widget.TextView",
      "scrollable": false,
      "selected": false,
      "long_clickable": false,
      "parent": 21,
      "temp_id": 27,
      "size": "996*57",
      "signature": "[class]android.widget.TextView[resource_id]com.habitrpg.android.habitica.debug:id/task_difficulty_title[text]Difficulty[enabled,,]",
      "view_str": "b61539c2848534bc24a4c786ff9ae4a8",
      "content_free_signature": "[class]android.widget.TextView[resource_id]com.habitrpg.android.habitica.debug:id/task_difficulty_title"
    },
    {
      "package": "com.habitrpg.android.habitica.debug",
      "visible": false,
      "checkable": false,
      "child_count": 4,
      "editable": false,
      "clickable": false,
      "is_password": false,
      "focusable": false,
      "enabled": true,
      "content_description": null,
      "children": [
        29,
        32,
        35,
        38
      ],
      "focused": false,
      "bounds": [
        [
          42,
          1097
        ],
        [
          1038,
          1319
        ]
      ],
      "resource_id": "com.habitrpg.android.habitica.debug:id/task_difficulty_buttons",
      "checked": false,
      "text": null,
      "class": "android.widget.LinearLayout",
      "scrollable": false,
      "selected": false,
      "long_clickable": false,
      "parent": 21,
      "temp_id": 28,
      "size": "996*222",
      "signature": "[class]android.widget.LinearLayout[resource_id]com.habitrpg.android.habitica.debug:id/task_difficulty_buttons[text]None[enabled,,]",
      "view_str": "0eab9e6d6c675c73ed9c68da1fd401a9",
      "content_free_signature": "[class]android.widget.LinearLayout[resource_id]com.habitrpg.android.habitica.debug:id/task_difficulty_buttons"
    },
    {
      "package": "com.habitrpg.android.habitica.debug",
      "visible": false,
      "checkable": false,
      "child_count": 2,
      "editable": false,
      "clickable": true,
      "is_password": false,
      "focusable": true,
      "enabled": true,
      "content_description": "Trivial, Not selected",
      "children": [
        30,
        31
      ],
      "focused": false,
      "bounds": [
        [
          42,
          1097
        ],
        [
          192,
          1319
        ]
      ],
      "resource_id": null,
      "checked": false,
      "text": null,
      "class": "android.widget.LinearLayout",
      "scrollable": false,
      "selected": false,
      "long_clickable": false,
      "parent": 28,
      "temp_id": 29,
      "size": "150*222",
      "signature": "[class]android.widget.LinearLayout[resource_id]None[text]None[enabled,,]",
      "view_str": "cf25e4cdc927b4c465eab753329dae0e",
      "content_free_signature": "[class]android.widget.LinearLayout[resource_id]None"
    },
    {
      "package": "com.habitrpg.android.habitica.debug",
      "visible": false,
      "checkable": false,
      "child_count": 0,
      "editable": false,
      "clickable": false,
      "is_password": false,
      "focusable": false,
      "enabled": true,
      "content_description": null,
      "children": [],
      "focused": false,
      "bounds": [
        [
          42,
          1097
        ],
        [
          192,
          1247
        ]
      ],
      "resource_id": "com.habitrpg.android.habitica.debug:id/image_view",
      "checked": false,
      "text": null,
      "class": "android.widget.ImageView",
      "scrollable": false,
      "selected": false,
      "long_clickable": false,
      "parent": 29,
      "temp_id": 30,
      "size": "150*150",
      "signature": "[class]android.widget.ImageView[resource_id]com.habitrpg.android.habitica.debug:id/image_view[text]None[enabled,,]",
      "view_str": "e6564c06383efb0675a9e79f40abea47",
      "content_free_signature": "[class]android.widget.ImageView[resource_id]com.habitrpg.android.habitica.debug:id/image_view"
    },
    {
      "package": "com.habitrpg.android.habitica.debug",
      "visible": false,
      "checkable": false,
      "child_count": 0,
      "editable": false,
      "clickable": false,
      "is_password": false,
      "focusable": false,
      "enabled": true,
      "content_description": null,
      "children": [],
      "focused": false,
      "bounds": [
        [
          67,
          1268
        ],
        [
          166,
          1319
        ]
      ],
      "resource_id": "com.habitrpg.android.habitica.debug:id/text_view",
      "checked": false,
      "text": "Trivial",
      "class": "android.widget.TextView",
      "scrollable": false,
      "selected": false,
      "long_clickable": false,
      "parent": 29,
      "temp_id": 31,
      "size": "99*51",
      "signature": "[class]android.widget.TextView[resource_id]com.habitrpg.android.habitica.debug:id/text_view[text]Trivial[enabled,,]",
      "view_str": "e295973f1ec2903b71151f4bee4a2992",
      "content_free_signature": "[class]android.widget.TextView[resource_id]com.habitrpg.android.habitica.debug:id/text_view"
    },
    {
      "package": "com.habitrpg.android.habitica.debug",
      "visible": false,
      "checkable": false,
      "child_count": 2,
      "editable": false,
      "clickable": true,
      "is_password": false,
      "focusable": true,
      "enabled": true,
      "content_description": "Easy, Selected",
      "children": [
        33,
        34
      ],
      "focused": false,
      "bounds": [
        [
          324,
          1097
        ],
        [
          474,
          1319
        ]
      ],
      "resource_id": null,
      "checked": false,
      "text": null,
      "class": "android.widget.LinearLayout",
      "scrollable": false,
      "selected": false,
      "long_clickable": false,
      "parent": 28,
      "temp_id": 32,
      "size": "150*222",
      "signature": "[class]android.widget.LinearLayout[resource_id]None[text]None[enabled,,]",
      "view_str": "f146a3a5af4e9daaa54f1c6ca642bdde",
      "content_free_signature": "[class]android.widget.LinearLayout[resource_id]None"
    },
    {
      "package": "com.habitrpg.android.habitica.debug",
      "visible": false,
      "checkable": false,
      "child_count": 0,
      "editable": false,
      "clickable": false,
      "is_password": false,
      "focusable": false,
      "enabled": true,
      "content_description": null,
      "children": [],
      "focused": false,
      "bounds": [
        [
          324,
          1097
        ],
        [
          474,
          1247
        ]
      ],
      "resource_id": "com.habitrpg.android.habitica.debug:id/image_view",
      "checked": false,
      "text": null,
      "class": "android.widget.ImageView",
      "scrollable": false,
      "selected": false,
      "long_clickable": false,
      "parent": 32,
      "temp_id": 33,
      "size": "150*150",
      "signature": "[class]android.widget.ImageView[resource_id]com.habitrpg.android.habitica.debug:id/image_view[text]None[enabled,,]",
      "view_str": "e6564c06383efb0675a9e79f40abea47",
      "content_free_signature": "[class]android.widget.ImageView[resource_id]com.habitrpg.android.habitica.debug:id/image_view"
    },
    {
      "package": "com.habitrpg.android.habitica.debug",
      "visible": false,
      "checkable": false,
      "child_count": 0,
      "editable": false,
      "clickable": false,
      "is_password": false,
      "focusable": false,
      "enabled": true,
      "content_description": null,
      "children": [],
      "focused": false,
      "bounds": [
        [
          360,
          1268
        ],
        [
          438,
          1319
        ]
      ],
      "resource_id": "com.habitrpg.android.habitica.debug:id/text_view",
      "checked": false,
      "text": "Easy",
      "class": "android.widget.TextView",
      "scrollable": false,
      "selected": false,
      "long_clickable": false,
      "parent": 32,
      "temp_id": 34,
      "size": "78*51",
      "signature": "[class]android.widget.TextView[resource_id]com.habitrpg.android.habitica.debug:id/text_view[text]Easy[enabled,,]",
      "view_str": "3f8b364382f90d4b41c3d75d7724f6f3",
      "content_free_signature": "[class]android.widget.TextView[resource_id]com.habitrpg.android.habitica.debug:id/text_view"
    },
    {
      "package": "com.habitrpg.android.habitica.debug",
      "visible": false,
      "checkable": false,
      "child_count": 2,
      "editable": false,
      "clickable": true,
      "is_password": false,
      "focusable": true,
      "enabled": true,
      "content_description": "Medium, Not selected",
      "children": [
        36,
        37
      ],
      "focused": false,
      "bounds": [
        [
          606,
          1097
        ],
        [
          756,
          1319
        ]
      ],
      "resource_id": null,
      "checked": false,
      "text": null,
      "class": "android.widget.LinearLayout",
      "scrollable": false,
      "selected": false,
      "long_clickable": false,
      "parent": 28,
      "temp_id": 35,
      "size": "150*222",
      "signature": "[class]android.widget.LinearLayout[resource_id]None[text]None[enabled,,]",
      "view_str": "996202a983ba404b9b51eadabe0d7761",
      "content_free_signature": "[class]android.widget.LinearLayout[resource_id]None"
    },
    {
      "package": "com.habitrpg.android.habitica.debug",
      "visible": false,
      "checkable": false,
      "child_count": 0,
      "editable": false,
      "clickable": false,
      "is_password": false,
      "focusable": false,
      "enabled": true,
      "content_description": null,
      "children": [],
      "focused": false,
      "bounds": [
        [
          606,
          1097
        ],
        [
          756,
          1247
        ]
      ],
      "resource_id": "com.habitrpg.android.habitica.debug:id/image_view",
      "checked": false,
      "text": null,
      "class": "android.widget.ImageView",
      "scrollable": false,
      "selected": false,
      "long_clickable": false,
      "parent": 35,
      "temp_id": 36,
      "size": "150*150",
      "signature": "[class]android.widget.ImageView[resource_id]com.habitrpg.android.habitica.debug:id/image_view[text]None[enabled,,]",
      "view_str": "e6564c06383efb0675a9e79f40abea47",
      "content_free_signature": "[class]android.widget.ImageView[resource_id]com.habitrpg.android.habitica.debug:id/image_view"
    },
    {
      "package": "com.habitrpg.android.habitica.debug",
      "visible": false,
      "checkable": false,
      "child_count": 0,
      "editable": false,
      "clickable": false,
      "is_password": false,
      "focusable": false,
      "enabled": true,
      "content_description": null,
      "children": [],
      "focused": false,
      "bounds": [
        [
          614,
          1268
        ],
        [
          748,
          1319
        ]
      ],
      "resource_id": "com.habitrpg.android.habitica.debug:id/text_view",
      "checked": false,
      "text": "Medium",
      "class": "android.widget.TextView",
      "scrollable": false,
      "selected": false,
      "long_clickable": false,
      "parent": 35,
      "temp_id": 37,
      "size": "134*51",
      "signature": "[class]android.widget.TextView[resource_id]com.habitrpg.android.habitica.debug:id/text_view[text]Medium[enabled,,]",
      "view_str": "a9ed03b3a752a2dab27de9731f1d51b4",
      "content_free_signature": "[class]android.widget.TextView[resource_id]com.habitrpg.android.habitica.debug:id/text_view"
    },
    {
      "package": "com.habitrpg.android.habitica.debug",
      "visible": false,
      "checkable": false,
      "child_count": 2,
      "editable": false,
      "clickable": true,
      "is_password": false,
      "focusable": true,
      "enabled": true,
      "content_description": "Hard, Not selected",
      "children": [
        39,
        40
      ],
      "focused": false,
      "bounds": [
        [
          888,
          1097
        ],
        [
          1038,
          1319
        ]
      ],
      "resource_id": null,
      "checked": false,
      "text": null,
      "class": "android.widget.LinearLayout",
      "scrollable": false,
      "selected": false,
      "long_clickable": false,
      "parent": 28,
      "temp_id": 38,
      "size": "150*222",
      "signature": "[class]android.widget.LinearLayout[resource_id]None[text]None[enabled,,]",
      "view_str": "ab91e144335aa799cf06571e0e3edd63",
      "content_free_signature": "[class]android.widget.LinearLayout[resource_id]None"
    },
    {
      "package": "com.habitrpg.android.habitica.debug",
      "visible": false,
      "checkable": false,
      "child_count": 0,
      "editable": false,
      "clickable": false,
      "is_password": false,
      "focusable": false,
      "enabled": true,
      "content_description": null,
      "children": [],
      "focused": false,
      "bounds": [
        [
          888,
          1097
        ],
        [
          1038,
          1247
        ]
      ],
      "resource_id": "com.habitrpg.android.habitica.debug:id/image_view",
      "checked": false,
      "text": null,
      "class": "android.widget.ImageView",
      "scrollable": false,
      "selected": false,
      "long_clickable": false,
      "parent": 38,
      "temp_id": 39,
      "size": "150*150",
      "signature": "[class]android.widget.ImageView[resource_id]com.habitrpg.android.habitica.debug:id/image_view[text]None[enabled,,]",
      "view_str": "e6564c06383efb0675a9e79f40abea47",
      "content_free_signature": "[class]android.widget.ImageView[resource_id]com.habitrpg.android.habitica.debug:id/image_view"
    },
    {
      "package": "com.habitrpg.android.habitica.debug",
      "visible": false,
      "checkable": false,
      "child_count": 0,
      "editable": false,
      "clickable": false,
      "is_password": false,
      "focusable": false,
      "enabled": true,
      "content_description": null,
      "children": [],
      "focused": false,
      "bounds": [
        [
          923,
          1268
        ],
        [
          1003,
          1319
        ]
      ],
      "resource_id": "com.habitrpg.android.habitica.debug:id/text_view",
      "checked": false,
      "text": "Hard",
      "class": "android.widget.TextView",
      "scrollable": false,
      "selected": false,
      "long_clickable": false,
      "parent": 38,
      "temp_id": 40,
      "size": "80*51",
      "signature": "[class]android.widget.TextView[resource_id]com.habitrpg.android.habitica.debug:id/text_view[text]Hard[enabled,,]",
      "view_str": "a2c9c0fead6599af67f169c36bc2ad3f",
      "content_free_signature": "[class]android.widget.TextView[resource_id]com.habitrpg.android.habitica.debug:id/text_view"
    },
    {
      "package": "com.habitrpg.android.habitica.debug",
      "visible": false,
      "checkable": false,
      "child_count": 0,
      "editable": false,
      "clickable": false,
      "is_password": false,
      "focusable": false,
      "enabled": true,
      "content_description": null,
      "children": [],
      "focused": false,
      "bounds": [
        [
          42,
          1361
        ],
        [
          1038,
          1418
        ]
      ],
      "resource_id": "com.habitrpg.android.habitica.debug:id/scheduling_title",
      "checked": false,
      "text": "Scheduling",
      "class": "android.widget.TextView",
      "scrollable": false,
      "selected": false,
      "long_clickable": false,
      "parent": 21,
      "temp_id": 41,
      "size": "996*57",
      "signature": "[class]android.widget.TextView[resource_id]com.habitrpg.android.habitica.debug:id/scheduling_title[text]Scheduling[enabled,,]",
      "view_str": "c16a9402950a0fab788b084b9ab6d8e4",
      "content_free_signature": "[class]android.widget.TextView[resource_id]com.habitrpg.android.habitica.debug:id/scheduling_title"
    },
    {
      "package": "com.habitrpg.android.habitica.debug",
      "visible": false,
      "checkable": false,
      "child_count": 4,
      "editable": false,
      "clickable": false,
      "is_password": false,
      "focusable": false,
      "enabled": true,
      "content_description": null,
      "children": [
        43,
        46,
        56,
        64
      ],
      "focused": false,
      "bounds": [
        [
          42,
          1439
        ],
        [
          1038,
          1794
        ]
      ],
      "resource_id": "com.habitrpg.android.habitica.debug:id/scheduling_controls",
      "checked": false,
      "text": null,
      "class": "android.widget.LinearLayout",
      "scrollable": false,
      "selected": false,
      "long_clickable": false,
      "parent": 21,
      "temp_id": 42,
      "size": "996*355",
      "signature": "[class]android.widget.LinearLayout[resource_id]com.habitrpg.android.habitica.debug:id/scheduling_controls[text]None[enabled,,]",
      "view_str": "b5023242e2aaf85dcbd1c77930e2270c",
      "content_free_signature": "[class]android.widget.LinearLayout[resource_id]com.habitrpg.android.habitica.debug:id/scheduling_controls"
    },
    {
      "package": "com.habitrpg.android.habitica.debug",
      "visible": false,
      "checkable": false,
      "child_count": 2,
      "editable": false,
      "clickable": true,
      "is_password": false,
      "focusable": true,
      "enabled": true,
      "content_description": null,
      "children": [
        44,
        45
      ],
      "focused": false,
      "bounds": [
        [
          42,
          1439
        ],
        [
          1038,
          1587
        ]
      ],
      "resource_id": "com.habitrpg.android.habitica.debug:id/start_date_wrapper",
      "checked": false,
      "text": null,
      "class": "android.widget.LinearLayout",
      "scrollable": false,
      "selected": false,
      "long_clickable": false,
      "parent": 42,
      "temp_id": 43,
      "size": "996*148",
      "signature": "[class]android.widget.LinearLayout[resource_id]com.habitrpg.android.habitica.debug:id/start_date_wrapper[text]None[enabled,,]",
      "view_str": "131fc3901bd9c0513e811084e849119a",
      "content_free_signature": "[class]android.widget.LinearLayout[resource_id]com.habitrpg.android.habitica.debug:id/start_date_wrapper"
    },
    {
      "package": "com.habitrpg.android.habitica.debug",
      "visible": false,
      "checkable": false,
      "child_count": 0,
      "editable": false,
      "clickable": false,
      "is_password": false,
      "focusable": false,
      "enabled": true,
      "content_description": null,
      "children": [],
      "focused": false,
      "bounds": [
        [
          84,
          1460
        ],
        [
          225,
          1503
        ]
      ],
      "resource_id": "com.habitrpg.android.habitica.debug:id/start_date_title",
      "checked": false,
      "text": "Start Date",
      "class": "android.widget.TextView",
      "scrollable": false,
      "selected": false,
      "long_clickable": false,
      "parent": 43,
      "temp_id": 44,
      "size": "141*43",
      "signature": "[class]android.widget.TextView[resource_id]com.habitrpg.android.habitica.debug:id/start_date_title[text]Start Date[enabled,,]",
      "view_str": "36283b5dc9a4122274cc46dca08f7fad",
      "content_free_signature": "[class]android.widget.TextView[resource_id]com.habitrpg.android.habitica.debug:id/start_date_title"
    },
    {
      "package": "com.habitrpg.android.habitica.debug",
      "visible": false,
      "checkable": false,
      "child_count": 0,
      "editable": false,
      "clickable": false,
      "is_password": false,
      "focusable": false,
      "enabled": true,
      "content_description": null,
      "children": [],
      "focused": false,
      "bounds": [
        [
          84,
          1503
        ],
        [
          996,
          1566
        ]
      ],
      "resource_id": "com.habitrpg.android.habitica.debug:id/start_date_textview",
      "checked": false,
      "text": "Aug 28, 2020",
      "class": "android.widget.TextView",
      "scrollable": false,
      "selected": false,
      "long_clickable": false,
      "parent": 43,
      "temp_id": 45,
      "size": "912*63",
      "signature": "[class]android.widget.TextView[resource_id]com.habitrpg.android.habitica.debug:id/start_date_textview[text]Aug 28, 2020[enabled,,]",
      "view_str": "7a20c454da8d7149aafde89f6958884e",
      "content_free_signature": "[class]android.widget.TextView[resource_id]com.habitrpg.android.habitica.debug:id/start_date_textview"
    },
    {
      "package": "com.habitrpg.android.habitica.debug",
      "visible": false,
      "checkable": false,
      "child_count": 2,
      "editable": false,
      "clickable": false,
      "is_password": false,
      "focusable": false,
      "enabled": true,
      "content_description": null,
      "children": [
        47,
        51
      ],
      "focused": false,
      "bounds": [
        [
          42,
          1629
        ],
        [
          1038,
          1794
        ]
      ],
      "resource_id": "com.habitrpg.android.habitica.debug:id/repeats_every_wrapper",
      "checked": false,
      "text": null,
      "class": "android.widget.LinearLayout",
      "scrollable": false,
      "selected": false,
      "long_clickable": false,
      "parent": 42,
      "temp_id": 46,
      "size": "996*165",
      "signature": "[class]android.widget.LinearLayout[resource_id]com.habitrpg.android.habitica.debug:id/repeats_every_wrapper[text]None[enabled,,]",
      "view_str": "2ddf9e9de1328794b31af933f25ee399",
      "content_free_signature": "[class]android.widget.LinearLayout[resource_id]com.habitrpg.android.habitica.debug:id/repeats_every_wrapper"
    },
    {
      "package": "com.habitrpg.android.habitica.debug",
      "visible": false,
      "checkable": false,
      "child_count": 2,
      "editable": false,
      "clickable": false,
      "is_password": false,
      "focusable": false,
      "enabled": true,
      "content_description": null,
      "children": [
        48,
        49
      ],
      "focused": false,
      "bounds": [
        [
          42,
          1629
        ],
        [
          519,
          1777
        ]
      ],
      "resource_id": null,
      "checked": false,
      "text": null,
      "class": "android.widget.LinearLayout",
      "scrollable": false,
      "selected": false,
      "long_clickable": false,
      "parent": 46,
      "temp_id": 47,
      "size": "477*148",
      "signature": "[class]android.widget.LinearLayout[resource_id]None[text]None[enabled,,]",
      "view_str": "468cd8c9ccbe2c1d2ad5f3c7000e4a65",
      "content_free_signature": "[class]android.widget.LinearLayout[resource_id]None"
    },
    {
      "package": "com.habitrpg.android.habitica.debug",
      "visible": false,
      "checkable": false,
      "child_count": 0,
      "editable": false,
      "clickable": false,
      "is_password": false,
      "focusable": false,
      "enabled": true,
      "content_description": null,
      "children": [],
      "focused": false,
      "bounds": [
        [
          84,
          1650
        ],
        [
          200,
          1693
        ]
      ],
      "resource_id": null,
      "checked": false,
      "text": "Repeats",
      "class": "android.widget.TextView",
      "scrollable": false,
      "selected": false,
      "long_clickable": false,
      "parent": 47,
      "temp_id": 48,
      "size": "116*43",
      "signature": "[class]android.widget.TextView[resource_id]None[text]Repeats[enabled,,]",
      "view_str": "04d49a0ed70d899d7547992e297f1045",
      "content_free_signature": "[class]android.widget.TextView[resource_id]None"
    },
    {
      "package": "com.habitrpg.android.habitica.debug",
      "visible": false,
      "checkable": false,
      "child_count": 1,
      "editable": false,
      "clickable": true,
      "is_password": false,
      "focusable": true,
      "enabled": true,
      "content_description": null,
      "children": [
        50
      ],
      "focused": false,
      "bounds": [
        [
          84,
          1693
        ],
        [
          477,
          1756
        ]
      ],
      "resource_id": "com.habitrpg.android.habitica.debug:id/repeats_every_spinner",
      "checked": false,
      "text": null,
      "class": "android.widget.Spinner",
      "scrollable": true,
      "selected": false,
      "long_clickable": true,
      "parent": 47,
      "temp_id": 49,
      "size": "393*63",
      "signature": "[class]android.widget.Spinner[resource_id]com.habitrpg.android.habitica.debug:id/repeats_every_spinner[text]None[enabled,,]",
      "view_str": "08efe3885f98d930e6aea311ca2b2bda",
      "content_free_signature": "[class]android.widget.Spinner[resource_id]com.habitrpg.android.habitica.debug:id/repeats_every_spinner"
    },
    {
      "package": "com.habitrpg.android.habitica.debug",
      "visible": false,
      "checkable": false,
      "child_count": 0,
      "editable": false,
      "clickable": false,
      "is_password": false,
      "focusable": false,
      "enabled": true,
      "content_description": null,
      "children": [],
      "focused": false,
      "bounds": [
        [
          84,
          1696
        ],
        [
          351,
          1753
        ]
      ],
      "resource_id": "android:id/text1",
      "checked": false,
      "text": "Weekly",
      "class": "android.widget.TextView",
      "scrollable": false,
      "selected": false,
      "long_clickable": false,
      "parent": 49,
      "temp_id": 50,
      "size": "267*57",
      "signature": "[class]android.widget.TextView[resource_id]android:id/text1[text]Weekly[enabled,,]",
      "view_str": "bdf278d18241071fbdbf9872c8971721",
      "content_free_signature": "[class]android.widget.TextView[resource_id]android:id/text1"
    },
    {
      "package": "com.habitrpg.android.habitica.debug",
      "visible": false,
      "checkable": false,
      "child_count": 2,
      "editable": false,
      "clickable": false,
      "is_password": false,
      "focusable": false,
      "enabled": true,
      "content_description": null,
      "children": [
        52,
        53
      ],
      "focused": false,
      "bounds": [
        [
          561,
          1629
        ],
        [
          1038,
          1771
        ]
      ],
      "resource_id": null,
      "checked": false,
      "text": null,
      "class": "android.widget.LinearLayout",
      "scrollable": false,
      "selected": false,
      "long_clickable": false,
      "parent": 46,
      "temp_id": 51,
      "size": "477*142",
      "signature": "[class]android.widget.LinearLayout[resource_id]None[text]None[enabled,,]",
      "view_str": "4170729041be703765dc8e0596cc2183",
      "content_free_signature": "[class]android.widget.LinearLayout[resource_id]None"
    },
    {
      "package": "com.habitrpg.android.habitica.debug",
      "visible": false,
      "checkable": false,
      "child_count": 0,
      "editable": false,
      "clickable": false,
      "is_password": false,
      "focusable": false,
      "enabled": true,
      "content_description": null,
      "children": [],
      "focused": false,
      "bounds": [
        [
          603,
          1650
        ],
        [
          680,
          1693
        ]
      ],
      "resource_id": null,
      "checked": false,
      "text": "Every",
      "class": "android.widget.TextView",
      "scrollable": false,
      "selected": false,
      "long_clickable": false,
      "parent": 51,
      "temp_id": 52,
      "size": "77*43",
      "signature": "[class]android.widget.TextView[resource_id]None[text]Every[enabled,,]",
      "view_str": "201d1045ec3fc340ebf433757479f636",
      "content_free_signature": "[class]android.widget.TextView[resource_id]None"
    },
    {
      "package": "com.habitrpg.android.habitica.debug",
      "visible": false,
      "checkable": false,
      "child_count": 2,
      "editable": false,
      "clickable": false,
      "is_password": false,
      "focusable": false,
      "enabled": true,
      "content_description": null,
      "children": [
        54,
        55
      ],
      "focused": false,
      "bounds": [
        [
          603,
          1693
        ],
        [
          996,
          1750
        ]
      ],
      "resource_id": null,
      "checked": false,
      "text": null,
      "class": "android.widget.LinearLayout",
      "scrollable": false,
      "selected": false,
      "long_clickable": false,
      "parent": 51,
      "temp_id": 53,
      "size": "393*57",
      "signature": "[class]android.widget.LinearLayout[resource_id]None[text]None[enabled,,]",
      "view_str": "6832b76b85a45d6e7aff28fa6136cf72",
      "content_free_signature": "[class]android.widget.LinearLayout[resource_id]None"
    },
    {
      "package": "com.habitrpg.android.habitica.debug",
      "visible": false,
      "checkable": false,
      "child_count": 0,
      "editable": true,
      "clickable": true,
      "is_password": false,
      "focusable": true,
      "enabled": true,
      "content_description": null,
      "children": [],
      "focused": false,
      "bounds": [
        [
          603,
          1693
        ],
        [
          885,
          1750
        ]
      ],
      "resource_id": "com.habitrpg.android.habitica.debug:id/repeats_every_edittext",
      "checked": false,
      "text": "1",
      "class": "android.widget.EditText",
      "scrollable": false,
      "selected": false,
      "long_clickable": true,
      "parent": 53,
      "temp_id": 54,
      "size": "282*57",
      "signature": "[class]android.widget.EditText[resource_id]com.habitrpg.android.habitica.debug:id/repeats_every_edittext[text]1[enabled,,]",
      "view_str": "86a355820bb1aa4737165811823babd4",
      "content_free_signature": "[class]android.widget.EditText[resource_id]com.habitrpg.android.habitica.debug:id/repeats_every_edittext"
    },
    {
      "package": "com.habitrpg.android.habitica.debug",
      "visible": false,
      "checkable": false,
      "child_count": 0,
      "editable": false,
      "clickable": false,
      "is_password": false,
      "focusable": false,
      "enabled": true,
      "content_description": null,
      "children": [],
      "focused": false,
      "bounds": [
        [
          885,
          1698
        ],
        [
          996,
          1749
        ]
      ],
      "resource_id": "com.habitrpg.android.habitica.debug:id/repeats_every_title",
      "checked": false,
      "text": "Weeks",
      "class": "android.widget.TextView",
      "scrollable": false,
      "selected": false,
      "long_clickable": false,
      "parent": 53,
      "temp_id": 55,
      "size": "111*51",
      "signature": "[class]android.widget.TextView[resource_id]com.habitrpg.android.habitica.debug:id/repeats_every_title[text]Weeks[enabled,,]",
      "view_str": "73fb7a01f6df8aed30c0c1163211041e",
      "content_free_signature": "[class]android.widget.TextView[resource_id]com.habitrpg.android.habitica.debug:id/repeats_every_title"
    },
    {
      "package": "com.habitrpg.android.habitica.debug",
      "visible": false,
      "checkable": false,
      "child_count": 7,
      "editable": false,
      "clickable": false,
      "is_password": false,
      "focusable": false,
      "enabled": true,
      "content_description": null,
      "children": [
        57,
        58,
        59,
        60,
        61,
        62,
        63
      ],
      "focused": false,
      "bounds": [
        [
          42,
          1819
        ],
        [
          1038,
          1794
        ]
      ],
      "resource_id": "com.habitrpg.android.habitica.debug:id/weekly_repeat_wrapper",
      "checked": false,
      "text": null,
      "class": "android.widget.LinearLayout",
      "scrollable": false,
      "selected": false,
      "long_clickable": false,
      "parent": 42,
      "temp_id": 56,
      "size": "996*-25",
      "signature": "[class]android.widget.LinearLayout[resource_id]com.habitrpg.android.habitica.debug:id/weekly_repeat_wrapper[text]None[enabled,,]",
      "view_str": "643726b8488621d443ae0e6396d6b57c",
      "content_free_signature": "[class]android.widget.LinearLayout[resource_id]com.habitrpg.android.habitica.debug:id/weekly_repeat_wrapper"
    },
    {
      "package": "com.habitrpg.android.habitica.debug",
      "visible": false,
      "checkable": false,
      "child_count": 0,
      "editable": false,
      "clickable": true,
      "is_password": false,
      "focusable": true,
      "enabled": true,
      "content_description": "Monday, Selected",
      "children": [],
      "focused": false,
      "bounds": [
        [
          42,
          1819
        ],
        [
          126,
          1794
        ]
      ],
      "resource_id": null,
      "checked": false,
      "text": "M",
      "class": "android.widget.TextView",
      "scrollable": false,
      "selected": false,
      "long_clickable": false,
      "parent": 56,
      "temp_id": 57,
      "size": "84*-25",
      "signature": "[class]android.widget.TextView[resource_id]None[text]M[enabled,,]",
      "view_str": "301ece0244fedf3177fa0244be3df84c",
      "content_free_signature": "[class]android.widget.TextView[resource_id]None"
    },
    {
      "package": "com.habitrpg.android.habitica.debug",
      "visible": false,
      "checkable": false,
      "child_count": 0,
      "editable": false,
      "clickable": true,
      "is_password": false,
      "focusable": true,
      "enabled": true,
      "content_description": "Tuesday, Selected",
      "children": [],
      "focused": false,
      "bounds": [
        [
          194,
          1819
        ],
        [
          278,
          1794
        ]
      ],
      "resource_id": null,
      "checked": false,
      "text": "T",
      "class": "android.widget.TextView",
      "scrollable": false,
      "selected": false,
      "long_clickable": false,
      "parent": 56,
      "temp_id": 58,
      "size": "84*-25",
      "signature": "[class]android.widget.TextView[resource_id]None[text]T[enabled,,]",
      "view_str": "5dfde6cd64acfd13421d1a7bd4e94ae9",
      "content_free_signature": "[class]android.widget.TextView[resource_id]None"
    },
    {
      "package": "com.habitrpg.android.habitica.debug",
      "visible": false,
      "checkable": false,
      "child_count": 0,
      "editable": false,
      "clickable": true,
      "is_password": false,
      "focusable": true,
      "enabled": true,
      "content_description": "Wednesday, Selected",
      "children": [],
      "focused": false,
      "bounds": [
        [
          346,
          1819
        ],
        [
          430,
          1794
        ]
      ],
      "resource_id": null,
      "checked": false,
      "text": "W",
      "class": "android.widget.TextView",
      "scrollable": false,
      "selected": false,
      "long_clickable": false,
      "parent": 56,
      "temp_id": 59,
      "size": "84*-25",
      "signature": "[class]android.widget.TextView[resource_id]None[text]W[enabled,,]",
      "view_str": "a9b7a891a37d21be6c33a4f8fd84235c",
      "content_free_signature": "[class]android.widget.TextView[resource_id]None"
    },
    {
      "package": "com.habitrpg.android.habitica.debug",
      "visible": false,
      "checkable": false,
      "child_count": 0,
      "editable": false,
      "clickable": true,
      "is_password": false,
      "focusable": true,
      "enabled": true,
      "content_description": "Thursday, Selected",
      "children": [],
      "focused": false,
      "bounds": [
        [
          498,
          1819
        ],
        [
          582,
          1794
        ]
      ],
      "resource_id": null,
      "checked": false,
      "text": "T",
      "class": "android.widget.TextView",
      "scrollable": false,
      "selected": false,
      "long_clickable": false,
      "parent": 56,
      "temp_id": 60,
      "size": "84*-25",
      "signature": "[class]android.widget.TextView[resource_id]None[text]T[enabled,,]",
      "view_str": "5dfde6cd64acfd13421d1a7bd4e94ae9",
      "content_free_signature": "[class]android.widget.TextView[resource_id]None"
    },
    {
      "package": "com.habitrpg.android.habitica.debug",
      "visible": false,
      "checkable": false,
      "child_count": 0,
      "editable": false,
      "clickable": true,
      "is_password": false,
      "focusable": true,
      "enabled": true,
      "content_description": "Friday, Selected",
      "children": [],
      "focused": false,
      "bounds": [
        [
          650,
          1819
        ],
        [
          734,
          1794
        ]
      ],
      "resource_id": null,
      "checked": false,
      "text": "F",
      "class": "android.widget.TextView",
      "scrollable": false,
      "selected": false,
      "long_clickable": false,
      "parent": 56,
      "temp_id": 61,
      "size": "84*-25",
      "signature": "[class]android.widget.TextView[resource_id]None[text]F[enabled,,]",
      "view_str": "95d4001eea00b4ab17ef59886be709a9",
      "content_free_signature": "[class]android.widget.TextView[resource_id]None"
    },
    {
      "package": "com.habitrpg.android.habitica.debug",
      "visible": false,
      "checkable": false,
      "child_count": 0,
      "editable": false,
      "clickable": true,
      "is_password": false,
      "focusable": true,
      "enabled": true,
      "content_description": "Saturday, Selected",
      "children": [],
      "focused": false,
      "bounds": [
        [
          802,
          1819
        ],
        [
          886,
          1794
        ]
      ],
      "resource_id": null,
      "checked": false,
      "text": "S",
      "class": "android.widget.TextView",
      "scrollable": false,
      "selected": false,
      "long_clickable": false,
      "parent": 56,
      "temp_id": 62,
      "size": "84*-25",
      "signature": "[class]android.widget.TextView[resource_id]None[text]S[enabled,,]",
      "view_str": "c7df2e126731e8de652e3c60f1c522b2",
      "content_free_signature": "[class]android.widget.TextView[resource_id]None"
    },
    {
      "package": "com.habitrpg.android.habitica.debug",
      "visible": false,
      "checkable": false,
      "child_count": 0,
      "editable": false,
      "clickable": true,
      "is_password": false,
      "focusable": true,
      "enabled": true,
      "content_description": "Sunday, Selected",
      "children": [],
      "focused": false,
      "bounds": [
        [
          954,
          1819
        ],
        [
          1038,
          1794
        ]
      ],
      "resource_id": null,
      "checked": false,
      "text": "S",
      "class": "android.widget.TextView",
      "scrollable": false,
      "selected": false,
      "long_clickable": false,
      "parent": 56,
      "temp_id": 63,
      "size": "84*-25",
      "signature": "[class]android.widget.TextView[resource_id]None[text]S[enabled,,]",
      "view_str": "c7df2e126731e8de652e3c60f1c522b2",
      "content_free_signature": "[class]android.widget.TextView[resource_id]None"
    },
    {
      "package": "com.habitrpg.android.habitica.debug",
      "visible": false,
      "checkable": false,
      "child_count": 0,
      "editable": false,
      "clickable": false,
      "is_password": false,
      "focusable": false,
      "enabled": true,
      "content_description": null,
      "children": [],
      "focused": false,
      "bounds": [
        [
          42,
          1924
        ],
        [
          1038,
          1794
        ]
      ],
      "resource_id": "com.habitrpg.android.habitica.debug:id/summary_textview",
      "checked": false,
      "text": "Repeats weekly every week  on Monday, Tuesday, Wednesday, Thursday, Friday, Saturday, Sunday",
      "class": "android.widget.TextView",
      "scrollable": false,
      "selected": false,
      "long_clickable": false,
      "parent": 42,
      "temp_id": 64,
      "size": "996*-130",
      "signature": "[class]android.widget.TextView[resource_id]com.habitrpg.android.habitica.debug:id/summary_textview[text]None[enabled,,]",
      "view_str": "026750e5d847d9f8d4437f6b6831bd25",
      "content_free_signature": "[class]android.widget.TextView[resource_id]com.habitrpg.android.habitica.debug:id/summary_textview"
    },
    {
      "package": "com.habitrpg.android.habitica.debug",
      "visible": false,
      "checkable": false,
      "child_count": 0,
      "editable": false,
      "clickable": false,
      "is_password": false,
      "focusable": false,
      "enabled": true,
      "content_description": null,
      "children": [],
      "focused": false,
      "bounds": [
        [
          42,
          2047
        ],
        [
          1038,
          1794
        ]
      ],
      "resource_id": "com.habitrpg.android.habitica.debug:id/adjust_streak_title",
      "checked": false,
      "text": "Adjust Streak",
      "class": "android.widget.TextView",
      "scrollable": false,
      "selected": false,
      "long_clickable": false,
      "parent": 21,
      "temp_id": 65,
      "size": "996*-253",
      "signature": "[class]android.widget.TextView[resource_id]com.habitrpg.android.habitica.debug:id/adjust_streak_title[text]Adjust Streak[enabled,,]",
      "view_str": "fcc89ee0392c081988cbd0473a690f37",
      "content_free_signature": "[class]android.widget.TextView[resource_id]com.habitrpg.android.habitica.debug:id/adjust_streak_title"
    },
    {
      "package": "com.habitrpg.android.habitica.debug",
      "visible": false,
      "checkable": false,
      "child_count": 2,
      "editable": false,
      "clickable": false,
      "is_password": false,
      "focusable": false,
      "enabled": true,
      "content_description": null,
      "children": [
        67,
        70
      ],
      "focused": false,
      "bounds": [
        [
          42,
          2125
        ],
        [
          1038,
          1794
        ]
      ],
      "resource_id": "com.habitrpg.android.habitica.debug:id/adjust_streak_wrapper",
      "checked": false,
      "text": null,
      "class": "android.widget.LinearLayout",
      "scrollable": false,
      "selected": false,
      "long_clickable": false,
      "parent": 21,
      "temp_id": 66,
      "size": "996*-331",
      "signature": "[class]android.widget.LinearLayout[resource_id]com.habitrpg.android.habitica.debug:id/adjust_streak_wrapper[text]None[enabled,,]",
      "view_str": "a4af6fe66f8bbf0c3fc8776618a09db0",
      "content_free_signature": "[class]android.widget.LinearLayout[resource_id]com.habitrpg.android.habitica.debug:id/adjust_streak_wrapper"
    },
    {
      "package": "com.habitrpg.android.habitica.debug",
      "visible": false,
      "checkable": false,
      "child_count": 1,
      "editable": false,
      "clickable": false,
      "is_password": false,
      "focusable": false,
      "enabled": true,
      "content_description": null,
      "children": [
        68
      ],
      "focused": false,
      "bounds": [
        [
          42,
          2125
        ],
        [
          511,
          1794
        ]
      ],
      "resource_id": null,
      "checked": false,
      "text": null,
      "class": "android.widget.LinearLayout",
      "scrollable": false,
      "selected": false,
      "long_clickable": false,
      "parent": 66,
      "temp_id": 67,
      "size": "469*-331",
      "signature": "[class]android.widget.LinearLayout[resource_id]None[text]None[enabled,,]",
      "view_str": "ddf41c761a2205b6612f2075a17e3576",
      "content_free_signature": "[class]android.widget.LinearLayout[resource_id]None"
    },
    {
      "package": "com.habitrpg.android.habitica.debug",
      "visible": false,
      "checkable": false,
      "child_count": 1,
      "editable": false,
      "clickable": false,
      "is_password": false,
      "focusable": false,
      "enabled": true,
      "content_description": null,
      "children": [
        69
      ],
      "focused": false,
      "bounds": [
        [
          42,
          2154
        ],
        [
          511,
          1794
        ]
      ],
      "resource_id": null,
      "checked": false,
      "text": null,
      "class": "android.widget.FrameLayout",
      "scrollable": false,
      "selected": false,
      "long_clickable": false,
      "parent": 67,
      "temp_id": 68,
      "size": "469*-360",
      "signature": "[class]android.widget.FrameLayout[resource_id]None[text]None[enabled,,]",
      "view_str": "e35775cabf26bc5f366c7da9e8485f2f",
      "content_free_signature": "[class]android.widget.FrameLayout[resource_id]None"
    },
    {
      "package": "com.habitrpg.android.habitica.debug",
      "visible": false,
      "checkable": false,
      "child_count": 0,
      "editable": true,
      "clickable": true,
      "is_password": false,
      "focusable": true,
      "enabled": true,
      "content_description": null,
      "children": [],
      "focused": false,
      "bounds": [
        [
          42,
          2154
        ],
        [
          511,
          1794
        ]
      ],
      "resource_id": "com.habitrpg.android.habitica.debug:id/habit_adjust_positive_streak",
      "checked": false,
      "text": "0",
      "class": "android.widget.EditText",
      "scrollable": false,
      "selected": false,
      "long_clickable": true,
      "parent": 68,
      "temp_id": 69,
      "size": "469*-360",
      "signature": "[class]android.widget.EditText[resource_id]com.habitrpg.android.habitica.debug:id/habit_adjust_positive_streak[text]0[enabled,,]",
      "view_str": "22b4c108b90a66d5b3819b5f5b31dd01",
      "content_free_signature": "[class]android.widget.EditText[resource_id]com.habitrpg.android.habitica.debug:id/habit_adjust_positive_streak"
    },
    {
      "package": "com.habitrpg.android.habitica.debug",
      "visible": false,
      "checkable": false,
      "child_count": 1,
      "editable": false,
      "clickable": false,
      "is_password": false,
      "focusable": false,
      "enabled": true,
      "content_description": null,
      "children": [
        71
      ],
      "focused": false,
      "bounds": [
        [
          569,
          2125
        ],
        [
          1038,
          1794
        ]
      ],
      "resource_id": null,
      "checked": false,
      "text": null,
      "class": "android.widget.LinearLayout",
      "scrollable": false,
      "selected": false,
      "long_clickable": false,
      "parent": 66,
      "temp_id": 70,
      "size": "469*-331",
      "signature": "[class]android.widget.LinearLayout[resource_id]None[text]None[enabled,,]",
      "view_str": "ddf41c761a2205b6612f2075a17e3576",
      "content_free_signature": "[class]android.widget.LinearLayout[resource_id]None"
    },
    {
      "package": "com.habitrpg.android.habitica.debug",
      "visible": false,
      "checkable": false,
      "child_count": 0,
      "editable": false,
      "clickable": false,
      "is_password": false,
      "focusable": false,
      "enabled": true,
      "content_description": null,
      "children": [],
      "focused": false,
      "bounds": [
        [
          569,
          2154
        ],
        [
          1038,
          1794
        ]
      ],
      "resource_id": null,
      "checked": false,
      "text": null,
      "class": "android.widget.FrameLayout",
      "scrollable": false,
      "selected": false,
      "long_clickable": false,
      "parent": 70,
      "temp_id": 71,
      "size": "469*-360",
      "signature": "[class]android.widget.FrameLayout[resource_id]None[text]None[enabled,,]",
      "view_str": "580ea9bcbecd2df10ecff5b3a4cb7c25",
      "content_free_signature": "[class]android.widget.FrameLayout[resource_id]None"
    },
    {
      "package": "com.habitrpg.android.habitica.debug",
      "visible": false,
      "checkable": false,
      "child_count": 0,
      "editable": false,
      "clickable": false,
      "is_password": false,
      "focusable": false,
      "enabled": true,
      "content_description": null,
      "children": [],
      "focused": false,
      "bounds": [
        [
          42,
          2354
        ],
        [
          1038,
          1794
        ]
      ],
      "resource_id": "com.habitrpg.android.habitica.debug:id/reminders_title",
      "checked": false,
      "text": "Reminders",
      "class": "android.widget.TextView",
      "scrollable": false,
      "selected": false,
      "long_clickable": false,
      "parent": 21,
      "temp_id": 72,
      "size": "996*-560",
      "signature": "[class]android.widget.TextView[resource_id]com.habitrpg.android.habitica.debug:id/reminders_title[text]Reminders[enabled,,]",
      "view_str": "8786cc7777d9842c6bd0deb34b479c6e",
      "content_free_signature": "[class]android.widget.TextView[resource_id]com.habitrpg.android.habitica.debug:id/reminders_title"
    },
    {
      "package": "com.habitrpg.android.habitica.debug",
      "visible": false,
      "checkable": false,
      "child_count": 1,
      "editable": false,
      "clickable": false,
      "is_password": false,
      "focusable": false,
      "enabled": true,
      "content_description": null,
      "children": [
        74
      ],
      "focused": false,
      "bounds": [
        [
          42,
          2432
        ],
        [
          1038,
          1794
        ]
      ],
      "resource_id": "com.habitrpg.android.habitica.debug:id/reminders_container",
      "checked": false,
      "text": null,
      "class": "android.widget.LinearLayout",
      "scrollable": false,
      "selected": false,
      "long_clickable": false,
      "parent": 21,
      "temp_id": 73,
      "size": "996*-638",
      "signature": "[class]android.widget.LinearLayout[resource_id]com.habitrpg.android.habitica.debug:id/reminders_container[text]None[enabled,,]",
      "view_str": "be31b6671fb15b25b08d9d7c1f1e1310",
      "content_free_signature": "[class]android.widget.LinearLayout[resource_id]com.habitrpg.android.habitica.debug:id/reminders_container"
    },
    {
      "package": "com.habitrpg.android.habitica.debug",
      "visible": false,
      "checkable": false,
      "child_count": 2,
      "editable": false,
      "clickable": false,
      "is_password": false,
      "focusable": false,
      "enabled": true,
      "content_description": null,
      "children": [
        75,
        76
      ],
      "focused": false,
      "bounds": [
        [
          42,
          2432
        ],
        [
          1038,
          1794
        ]
      ],
      "resource_id": null,
      "checked": false,
      "text": null,
      "class": "android.widget.LinearLayout",
      "scrollable": false,
      "selected": false,
      "long_clickable": false,
      "parent": 73,
      "temp_id": 74,
      "size": "996*-638",
      "signature": "[class]android.widget.LinearLayout[resource_id]None[text]None[enabled,,]",
      "view_str": "2595ada5ceb08353ebec7de81ff5647a",
      "content_free_signature": "[class]android.widget.LinearLayout[resource_id]None"
    },
    {
      "package": "com.habitrpg.android.habitica.debug",
      "visible": false,
      "checkable": false,
      "child_count": 0,
      "editable": false,
      "clickable": true,
      "is_password": false,
      "focusable": true,
      "enabled": true,
      "content_description": "Delete Reminder",
      "children": [],
      "focused": false,
      "bounds": [
        [
          42,
          2442
        ],
        [
          142,
          1794
        ]
      ],
      "resource_id": "com.habitrpg.android.habitica.debug:id/button",
      "checked": false,
      "text": null,
      "class": "android.widget.ImageButton",
      "scrollable": false,
      "selected": false,
      "long_clickable": false,
      "parent": 74,
      "temp_id": 75,
      "size": "100*-648",
      "signature": "[class]android.widget.ImageButton[resource_id]com.habitrpg.android.habitica.debug:id/button[text]None[enabled,,]",
      "view_str": "a8bed7071db30e761a74529b16746318",
      "content_free_signature": "[class]android.widget.ImageButton[resource_id]com.habitrpg.android.habitica.debug:id/button"
    },
    {
      "package": "com.habitrpg.android.habitica.debug",
      "visible": false,
      "checkable": false,
      "child_count": 0,
      "editable": false,
      "clickable": true,
      "is_password": false,
      "focusable": true,
      "enabled": true,
      "content_description": null,
      "children": [],
      "focused": false,
      "bounds": [
        [
          184,
          2456
        ],
        [
          1038,
          1794
        ]
      ],
      "resource_id": "com.habitrpg.android.habitica.debug:id/text_view",
      "checked": false,
      "text": "New reminder",
      "class": "android.widget.TextView",
      "scrollable": false,
      "selected": false,
      "long_clickable": false,
      "parent": 74,
      "temp_id": 76,
      "size": "854*-662",
      "signature": "[class]android.widget.TextView[resource_id]com.habitrpg.android.habitica.debug:id/text_view[text]New reminder[enabled,,]",
      "view_str": "59051b80bb92c66c0eb32953d90d1f38",
      "content_free_signature": "[class]android.widget.TextView[resource_id]com.habitrpg.android.habitica.debug:id/text_view"
    },
    {
      "package": "com.habitrpg.android.habitica.debug",
      "visible": false,
      "checkable": false,
      "child_count": 0,
      "editable": false,
      "clickable": false,
      "is_password": false,
      "focusable": false,
      "enabled": true,
      "content_description": null,
      "children": [],
      "focused": false,
      "bounds": [
        [
          42,
          2595
        ],
        [
          1038,
          1794
        ]
      ],
      "resource_id": "com.habitrpg.android.habitica.debug:id/tags_title",
      "checked": false,
      "text": "Tags",
      "class": "android.widget.TextView",
      "scrollable": false,
      "selected": false,
      "long_clickable": false,
      "parent": 21,
      "temp_id": 77,
      "size": "996*-801",
      "signature": "[class]android.widget.TextView[resource_id]com.habitrpg.android.habitica.debug:id/tags_title[text]Tags[enabled,,]",
      "view_str": "eaf5db464363f5f823771e71aedfb0ca",
      "content_free_signature": "[class]android.widget.TextView[resource_id]com.habitrpg.android.habitica.debug:id/tags_title"
    },
    {
      "package": "com.habitrpg.android.habitica.debug",
      "visible": false,
      "checkable": false,
      "child_count": 0,
      "editable": false,
      "clickable": false,
      "is_password": false,
      "focusable": false,
      "enabled": true,
      "content_description": null,
      "children": [],
      "focused": false,
      "bounds": [
        [
          42,
          2673
        ],
        [
          1038,
          1794
        ]
      ],
      "resource_id": "com.habitrpg.android.habitica.debug:id/tags_wrapper",
      "checked": false,
      "text": null,
      "class": "android.widget.LinearLayout",
      "scrollable": false,
      "selected": false,
      "long_clickable": false,
      "parent": 21,
      "temp_id": 78,
      "size": "996*-879",
      "signature": "[class]android.widget.LinearLayout[resource_id]com.habitrpg.android.habitica.debug:id/tags_wrapper[text]None[enabled,,]",
      "view_str": "5b0a187df62f99838df3244f49a4a0b4",
      "content_free_signature": "[class]android.widget.LinearLayout[resource_id]com.habitrpg.android.habitica.debug:id/tags_wrapper"
    },
    {
      "package": "com.habitrpg.android.habitica.debug",
      "visible": false,
      "checkable": false,
      "child_count": 0,
      "editable": false,
      "clickable": false,
      "is_password": false,
      "focusable": false,
      "enabled": true,
      "content_description": null,
      "children": [],
      "focused": false,
      "bounds": [
        [
          0,
          0
        ],
        [
          1080,
          63
        ]
      ],
      "resource_id": "android:id/statusBarBackground",
      "checked": false,
      "text": null,
      "class": "android.view.View",
      "scrollable": false,
      "selected": false,
      "long_clickable": false,
      "parent": 0,
      "temp_id": 79,
      "size": "1080*63",
      "signature": "[class]android.view.View[resource_id]android:id/statusBarBackground[text]None[enabled,,]",
      "view_str": "514188d6ae32d832b0a7e7bf36739af4",
      "content_free_signature": "[class]android.view.View[resource_id]android:id/statusBarBackground"
    },
    {
      "package": "com.habitrpg.android.habitica.debug",
      "visible": false,
      "checkable": false,
      "child_count": 0,
      "editable": false,
      "clickable": false,
      "is_password": false,
      "focusable": false,
      "enabled": true,
      "content_description": null,
      "children": [],
      "focused": false,
      "bounds": [
        [
          0,
          1794
        ],
        [
          1080,
          1920
        ]
      ],
      "resource_id": "android:id/navigationBarBackground",
      "checked": false,
      "text": null,
      "class": "android.view.View",
      "scrollable": false,
      "selected": false,
      "long_clickable": false,
      "parent": 0,
      "temp_id": 80,
      "size": "1080*126",
      "signature": "[class]android.view.View[resource_id]android:id/navigationBarBackground[text]None[enabled,,]",
      "view_str": "81b97e038513a3e20a99117a34f7e917",
      "content_free_signature": "[class]android.view.View[resource_id]android:id/navigationBarBackground"
    }
  ]
}